circadian_desktops/__init__.py
circadian_desktops/__main__.py
circadian_desktops/app.py
circadian_desktops/clean.py
circadian_desktops/custom_qt.py
circadian_desktops/desktopUi.ui
circadian_desktops/functions.py
circadian_desktops/ui_mainwindow.py
circadian_desktops/icons/clock.png
circadian_desktops/icons/clock_32.png
circadian_desktops/icons/clock_50.png
circadian_desktops/icons/dawn.png
circadian_desktops/icons/dawn_64.png
circadian_desktops/icons/dawn_80.png
circadian_desktops/icons/day.png
circadian_desktops/icons/day_64.png
circadian_desktops/icons/day_80.png
circadian_desktops/icons/dusk.png
circadian_desktops/icons/dusk_64.png
circadian_desktops/icons/dusk_80.png
circadian_desktops/icons/logo.ico
circadian_desktops/icons/logo.png
circadian_desktops/icons/night.png
circadian_desktops/icons/night_64.png
circadian_desktops/icons/night_80.png
circadian_desktops/icons/preferences.png
circadian_desktops/icons/preferences_32.png
circadian_desktops/icons/preferences_50.png
circadian_desktops/icons/screen.png
circadian_desktops/icons/screen_32.png
circadian_desktops/icons/screen_50.png
circadian_desktops-0.1.1.dist-info/METADATA
circadian_desktops-0.1.1.dist-info/WHEEL
circadian_desktops-0.1.1.dist-info/licenses/LICENSE
circadian_desktops-0.1.1.dist-info/RECORD
