Metadata-Version: 2.1
Name: circadian_desktops
Version: 0.1.1
Summary: An app that changes your desktop background based on time of day.
Project-URL: Homepage, https://github.com/Luke943/CircadianDesktops
Project-URL: Bug Tracker, https://github.com/Luke943/CircadianDesktops/issues
License-File: LICENSE
Classifier: License :: OSI Approved :: MIT License
Classifier: Operating System :: Microsoft :: Windows :: Windows 10
Classifier: Programming Language :: Python :: 3
Requires-Python: >=3.8
Requires-Dist: astral
Requires-Dist: geocoder
Requires-Dist: pyqt5
